inventree_manufacturing_costs-0.1.1.dist-info/licenses/LICENSE
manufacturing_costs/__init__.py
manufacturing_costs/admin.py
manufacturing_costs/apps.py
manufacturing_costs/core.py
manufacturing_costs/models.py
manufacturing_costs/serializers.py
manufacturing_costs/views.py
manufacturing_costs/migrations/0001_initial.py
manufacturing_costs/migrations/0002_remove_manufacturingcost_amortization_and_more.py
manufacturing_costs/migrations/0003_manufacturingcost_description.py
manufacturing_costs/migrations/0004_manufacturingcost_active_manufacturingcost_inherited.py
manufacturing_costs/migrations/__init__.py
manufacturing_costs/static/AdminPanel.js
manufacturing_costs/static/AdminPanel.js.map
manufacturing_costs/static/PartPanel.js
manufacturing_costs/static/PartPanel.js.map
manufacturing_costs/static/.vite/manifest.json
manufacturing_costs/static/assets/index-BjwOiYns.js
manufacturing_costs/static/assets/index-BjwOiYns.js.map
inventree_manufacturing_costs-0.1.1.dist-info/METADATA
inventree_manufacturing_costs-0.1.1.dist-info/WHEEL
inventree_manufacturing_costs-0.1.1.dist-info/entry_points.txt
inventree_manufacturing_costs-0.1.1.dist-info/top_level.txt
inventree_manufacturing_costs-0.1.1.dist-info/RECORD
