Metadata-Version: 2.4
Name: inventree-manufacturing-costs
Version: 0.1.1
Summary: Capture part manufacturing costs
Home-page: https://github.com/SchrodingersGat/inventree-manufacturing-costs
Author: Oliver Walters
Author-email: oliver.henry.walters@gmail.com
License: MIT
Keywords: inventree plugin
Classifier: Programming Language :: Python :: 3
Classifier: Operating System :: OS Independent
Classifier: Framework :: InvenTree
Requires-Python: >=3.9
License-File: LICENSE
Dynamic: author
Dynamic: author-email
Dynamic: classifier
Dynamic: description
Dynamic: description-content-type
Dynamic: home-page
Dynamic: keywords
Dynamic: license
Dynamic: license-file
Dynamic: requires-python
Dynamic: summary
